filestostorage/__init__.py
filestostorage-0.0.2.7.dist-info/LICENCE
filestostorage-0.0.2.7.dist-info/METADATA
filestostorage-0.0.2.7.dist-info/WHEEL
filestostorage-0.0.2.7.dist-info/top_level.txt
filestostorage-0.0.2.7.dist-info/RECORD
