Metadata-Version: 2.1
Name: filestostorage
Version: 0.0.2.7
Summary: package for file storage
Author: ngit_kmit
Author-email: devikarubir@gmail.com
Keywords: mongodb,store files,database,store,file,ngit,mongo,kmit
Classifier: Development Status :: 1 - Planning
Classifier: Intended Audience :: Developers
Classifier: Programming Language :: Python :: 3
Classifier: Operating System :: Unix
Classifier: Operating System :: MacOS :: MacOS X
Classifier: Operating System :: Microsoft :: Windows
Classifier: Topic :: Database
Classifier: Topic :: Software Development :: Libraries :: Python Modules
Classifier: Intended Audience :: Developers
Classifier: License :: OSI Approved :: MIT License
License-File: LICENCE
Requires-Dist: gridfs
Requires-Dist: certifi
Requires-Dist: pymongo
